meshctrl/__init__.py
meshctrl/meshctrl.py
meshctrl/utils.py
meshctrl-0.1.15.dist-info/LICENSE
meshctrl-0.1.15.dist-info/METADATA
meshctrl-0.1.15.dist-info/WHEEL
meshctrl-0.1.15.dist-info/top_level.txt
meshctrl-0.1.15.dist-info/RECORD
