Metadata-Version: 2.1
Name: meshctrl
Version: 0.1.15
Summary: Python port of MeshCentral's Meshctrl.js program
Home-page: https://github.com/amidaware/meshctrl-py
Author: Josh Krawczyk
Author-email: josh@torchlake.com
License: MIT
Platform: UNKNOWN
Classifier: Programming Language :: Python :: 3
Classifier: License :: OSI Approved :: MIT License
Classifier: Operating System :: OS Independent
Requires-Python: >=3.6
License-File: LICENSE
Requires-Dist: websockets (>=10.2)
Requires-Dist: pycryptodome (>=3.14.1)
